sophos/__init__.py
sophos-0.0.1.dist-info/LICENSE
sophos-0.0.1.dist-info/METADATA
sophos-0.0.1.dist-info/WHEEL
sophos-0.0.1.dist-info/top_level.txt
sophos-0.0.1.dist-info/RECORD
