Metadata-Version: 2.1
Name: sophos
Version: 0.0.1
Summary: σοφός (sophós), in classical philosophy, is someone who has attained wisdom.
Author-email: Alexander Fedotov <alex.fedotov@aol.com>
Project-URL: Homepage, https://github.com/alxfed/sophos
Project-URL: Bug Tracker, https://github.com/alxfed/sophos/issues
Classifier: Programming Language :: Python :: 3
Classifier: License :: OSI Approved :: MIT License
Classifier: Operating System :: OS Independent
Requires-Python: >=3.10
License-File: LICENSE
